{
	"id": "1035bd39-11e2-47d6-8b45-01d60870d319",
	"name": "oop2pg1db",
	"values": [
		{
			"key": "jwtToken",
			"value": "",
			"type": "default",
			"enabled": true
		},
		{
			"key": "siteUrl",
			"value": "http://localhost:8080",
			"type": "default",
			"enabled": true
		},
		{
			"key": "lastSiteId",
			"value": "lastSiteId",
			"enabled": true
		},
		{
			"key": "clientUrl",
			"value": "http://localhost:3030",
			"type": "default",
			"enabled": true
		},
		{
			"key": "lastSiteId",
			"value": "",
			"type": "any",
			"enabled": true
		},
		{
			"key": "lastMalakiId",
			"value": "",
			"type": "any",
			"enabled": true
		}
	],
	"_postman_variable_scope": "environment",
	"_postman_exported_at": "2022-04-10T13:14:21.870Z",
	"_postman_exported_using": "Postman/9.15.11"
}